lupo/__init__.py
lupo/core/lupo_window.py
lupo/core/view.py
lupo/core/osx/osx_display.py
lupo/core/osx/osx_override.py
lupo/core/osx/osx_structs.py
lupo/core/osx/osx_window_manager.py
lupo/core/win32/win32_display.py
lupo/core/win32/win32_structs.py
lupo/core/win32/win32_window_manager.py
lupo/styling/__init__.py
lupo/styling/applier.py
lupo/styling/color.py
lupo/styling/style.py
lupo/views/button.py
lupo/views/column.py
lupo/views/row.py
lupo/views/text.py
lupo-0.0.3.4.dist-info/METADATA
lupo-0.0.3.4.dist-info/WHEEL
lupo-0.0.3.4.dist-info/licenses/LICENSE
lupo-0.0.3.4.dist-info/RECORD
