Metadata-Version: 2.1
Name: lupo
Version: 0.0.3.4
Summary: A Python Framework for creating Cross-Platform Desktop Applications
Author-email: Anthony Hofmeister <me@anthonyhfm.dev>
License-File: LICENSE
Classifier: License :: OSI Approved :: MIT License
Classifier: Operating System :: OS Independent
Classifier: Programming Language :: Python :: 3
Requires-Python: >=3.7
Requires-Dist: pyobjc-core>=0.8.5; sys_platform == 'darwin'
Requires-Dist: pyobjc-framework-cocoa>=0.8.5; sys_platform == 'darwin'
Requires-Dist: pywin32>=304; sys_platform == 'win32'
